{
  "snippets": [
    {
      "title": "Git",
      "code": "git pull\ngit clone\ncode .\ngit add --all\ngit commit -m “int”\ngit push\ngit push origin main:new"
    },
    {
      "title": "Jupyter",
      "code": "jupyter-lab\njupyter notebook\n"
    },
    {
      "title": "PiP",
      "code": "pip install numpy\npip install pandas\npip install matplotlib\npip install seaborn\npip install scipy\npip install statsmodels\npip install scikit-learn"
    },
    {
      "title": "Jekyll",
      "code": "bundle lock --add-platform x86_64-linux\nbundle\nbundle exec jekyll serve"
    },
    {
      "title": "R",
      "code": "install.packages(\"forecast\")\ninstall.packages(\"tseries\")\ninstall.packages(\"zoo\")\nlibrary(forecast)\nlibrary(tseries)\nlibrary(zoo)"
    },
    {
      "title": "Viewport",
      "code": "<meta name=\"viewport\" content=\"width=device-width, initial-scale=1.0\">\n"
    },
    {
      "title": "Style",
      "code": "<style>\n\n</style>"
    },
    {
      "title": "Script",
      "code": "<script>\n \n</script> "
    },
    {
      "title": "!HTML Boiler",
      "code": "<!DOCTYPE html>\n <html  lang=\"en\"> \n <head> \n    <meta charset=\"UTF-8\">\n    <meta name=\"viewport\" content=\"width=device-width, initial-scale=1.0\">\n    <title>Document</title>\n\n </head>\n <body>    \n </body> \n </html>"
    }
   
   
   
   
   
   
   
   
  ]
}
